regressout/__init__.py
regressout-0.0.1.dist-info/LICENSE
regressout-0.0.1.dist-info/METADATA
regressout-0.0.1.dist-info/WHEEL
regressout-0.0.1.dist-info/top_level.txt
regressout-0.0.1.dist-info/RECORD
